setup.py
django_ratchet/__init__.py
django_ratchet/context_processors.py
django_ratchet/middleware.py
django_ratchet/models.py
django_ratchet/tests.py
django_ratchet.egg-info/PKG-INFO
django_ratchet.egg-info/SOURCES.txt
django_ratchet.egg-info/dependency_links.txt
django_ratchet.egg-info/requires.txt
django_ratchet.egg-info/top_level.txt