Metadata-Version: 1.0
Name: django-ratchet
Version: 0.3.4
Summary: Ratchet.io plugin for django
Home-page: http://github.com/brianr/django_ratchet
Author: Brian Rue
Author-email: brian@ratchet.io
License: UNKNOWN
Platform: UNKNOWN
Classifier: Programming Language :: Python
Classifier: License :: OSI Approved :: MIT License
Classifier: Operating System :: OS Independent
Classifier: Development Status :: 4 - Beta
Classifier: Environment :: Web Environment
Classifier: Framework :: Django
Classifier: Intended Audience :: Developers
Classifier: Topic :: Internet :: WWW/HTTP
Classifier: Topic :: Internet :: WWW/HTTP :: WSGI :: Middleware
Classifier: Topic :: Software Development
Classifier: Topic :: Software Development :: Bug Tracking
Classifier: Topic :: Software Development :: Testing
Classifier: Topic :: Software Development :: Quality Assurance
